absl_extra/__init__.py
absl_extra/callbacks.py
absl_extra/clu_utils.py
absl_extra/cuda_utils.py
absl_extra/flax_utils.py
absl_extra/logging_utils.py
absl_extra/notifier.py
absl_extra/py.typed
absl_extra/tasks.py
absl_extra/tf_utils.py
absl_extra/typing_utils.py
absl_extra-0.1.3.dist-info/WHEEL
absl_extra-0.1.3.dist-info/METADATA
absl_extra-0.1.3.dist-info/RECORD
