Metadata-Version: 2.1
Name: absl_extra
Version: 0.1.3
Summary: A wrapper to run and monitor absl app.
Author-email: Artem Sereda <artem.sereda.tub@gmail.com>
Maintainer-email: Artem Sereda <artem.sereda.tub@gmail.com>
Requires-Python: >=3.8
Classifier: Development Status :: 3 - Alpha
Requires-Dist: absl_py
Requires-Dist: toolz
Requires-Dist: typing_extensions; python_version < '3.10'
Requires-Dist: clu ; extra == "clu"
Requires-Dist: nvidia-ml-py ; extra == "cuda"
Requires-Dist: black ; extra == "dev"
Requires-Dist: pytest ; extra == "dev"
Requires-Dist: chex ; extra == "dev"
Requires-Dist: absl_extra[mongo,ml_collections,slack,tensorflow,jax,flax] ; extra == "dev"
Requires-Dist: ruff ; extra == "dev"
Requires-Dist: mypy==1.4.1 ; extra == "dev"
Requires-Dist: clu ; extra == "dev"
Requires-Dist: absl_extra[jax] ; extra == "flax"
Requires-Dist: flax ; extra == "flax"
Requires-Dist: tqdm ; extra == "flax"
Requires-Dist: jax ; extra == "jax"
Requires-Dist: jaxlib ; extra == "jax"
Requires-Dist: ml_collections ; extra == "ml_collections"
Requires-Dist: pymongo ; extra == "mongo"
Requires-Dist: slack_sdk ; extra == "slack"
Requires-Dist: tensorflow ; extra == "tensorflow" and ( sys_platform == 'linux')
Requires-Dist: tensorflow_macos ; extra == "tensorflow" and ( sys_platform == 'darwin')
Project-URL: Homepage, https://github.com/aaarrti/absl_extra
Provides-Extra: clu
Provides-Extra: cuda
Provides-Extra: dev
Provides-Extra: flax
Provides-Extra: jax
Provides-Extra: ml_collections
Provides-Extra: mongo
Provides-Extra: slack
Provides-Extra: tensorflow
